cmShoppingList/__init__.py
cmShoppingList/admin.py
cmShoppingList/app_settings.py
cmShoppingList/apps.py
cmShoppingList/auth_hooks.py
cmShoppingList/models.py
cmShoppingList/tasks.py
cmShoppingList/urls.py
cmShoppingList/views.py
cmShoppingList/management/__init__.py
cmShoppingList/management/commands/populate_types.py
cmShoppingList/management/commands/data/market_types.tsv
cmShoppingList/migrations/0001_initial.py
cmShoppingList/migrations/0002_itemequivalence.py
cmShoppingList/migrations/__init__.py
cmShoppingList/static/cmShoppingList/components/ShoppingList.js
cmShoppingList/static/cmShoppingList/css/main.css
cmShoppingList/static/cmShoppingList/scripts/parse.js
cmShoppingList/templates/cmShoppingList/base.html
cmShoppingList/templates/cmShoppingList/index.html
cmShoppingList/templates/cmShoppingList/vue/shoppinglist-component.html
cmshoppinglist-0.21.dist-info/licenses/LICENSE
cmshoppinglist-0.21.dist-info/WHEEL
cmshoppinglist-0.21.dist-info/METADATA
cmshoppinglist-0.21.dist-info/RECORD
